streamlit_jupyter_magic/__init__.py
streamlit_jupyter_magic/_version.py
streamlit_jupyter_magic/server.py
streamlit_jupyter_magic/utils.py
streamlit_jupyter_magic-1.2.1.dist-info/LICENSE
streamlit_jupyter_magic-1.2.1.dist-info/METADATA
streamlit_jupyter_magic-1.2.1.dist-info/WHEEL
streamlit_jupyter_magic-1.2.1.dist-info/top_level.txt
streamlit_jupyter_magic-1.2.1.dist-info/RECORD
