Metadata-Version: 2.1
Name: streamlit-jupyter-magic
Version: 1.2.1
Summary: Streamlit for Jupyter environments
Home-page: https://github.com/comet-ml/streamlit-jupyter-magic
Author: Streamlit Jupyter Magic Development Team
License: Apache 2.0 License
Keywords: data science,python
Platform: Linux
Platform: Mac OS X
Platform: Windows
Classifier: License :: OSI Approved :: Apache Software License
Classifier: Programming Language :: Python
Classifier: Programming Language :: Python :: 3
Classifier: Programming Language :: Python :: 3.9
Classifier: Programming Language :: Python :: 3.10
Classifier: Framework :: Jupyter
Requires-Python: >=3.7
License-File: LICENSE
Requires-Dist: streamlit
Requires-Dist: rich
Requires-Dist: psutil
Requires-Dist: matplotlib
Requires-Dist: numpy
